clap_python/__init__.py
clap_python/style.py
clap_python/complete/__init__.py
clap_python/complete/__main__.py
clap_python/complete/_register_app.py
clap_python-0.2.4.dist-info/METADATA
clap_python-0.2.4.dist-info/WHEEL
clap_python-0.2.4.dist-info/entry_points.txt
clap_python-0.2.4.dist-info/licenses/LICENSE
clap_python-0.2.4.dist-info/RECORD
