Metadata-Version: 2.4
Name: clap_python
Version: 0.2.4
Summary: Rust Clap inspired command line argument parser.
Project-URL: Homepage, https://github.com/maxWiklund/clap-python
Project-URL: Documentation, https://clap-python.readthedocs.io/en/latest
Project-URL: Repository, https://github.com/maxWiklund/clap-python.git
Project-URL: Bug Tracker, https://github.com/maxWiklund/clap-python/issues
Author: Max Wiklund
Maintainer: Max Wiklund
License:                                  Apache License
License-File: LICENSE
Keywords: Command line argument parser.,cli
Classifier: Development Status :: 4 - Beta
Classifier: Intended Audience :: Developers
Classifier: License :: OSI Approved :: Apache Software License
Classifier: Operating System :: OS Independent
Classifier: Programming Language :: Python
Classifier: Typing :: Typed
Requires-Python: >=3.7
Requires-Dist: importlib-metadata; python_version < '3.8'
